phileas-0.5.dist-info/METADATA
phileas-0.5.dist-info/WHEEL
phileas-0.5.dist-info/entry_points.txt
phileas-0.5.dist-info/licenses/license
phileas/__init__.py
phileas/__main__.py
phileas/_rust.cpython-312-darwin.so
phileas/_rust.pyi
phileas/benchmark.py
phileas/factory.py
phileas/iteration/__init__.py
phileas/iteration/base.py
phileas/iteration/leaf.py
phileas/iteration/node.py
phileas/iteration/random.py
phileas/iteration/utility.py
phileas/logging.py
phileas/mock_instruments.py
phileas/parsing.py
phileas/templates/bench.yaml.template
phileas/templates/experiment.yaml.template
phileas/templates/script.py.template
phileas/utility.py
phileas-0.5.dist-info/RECORD
