Metadata-Version: 2.4
Name: phileas
Version: 0.5
Classifier: Development Status :: 4 - Beta
Classifier: Intended Audience :: Science/Research
Classifier: Intended Audience :: Developers
Classifier: Intended Audience :: Information Technology
Classifier: License :: OSI Approved :: MIT License
Classifier: Natural Language :: English
Classifier: Programming Language :: Rust
Classifier: Programming Language :: Python :: 3
Classifier: Programming Language :: Python :: 3.10
Classifier: Programming Language :: Python :: 3.11
Classifier: Programming Language :: Python :: 3.12
Classifier: Programming Language :: Python :: 3.13
Classifier: Programming Language :: Python :: Implementation :: CPython
Classifier: Programming Language :: Python :: Implementation :: PyPy
Classifier: Topic :: Security
Requires-Dist: graphviz>=0.21,<0.22
Requires-Dist: rich>=14.1.0,<15.0.0
Requires-Dist: ruamel-yaml>=0.18.14,<0.19.0
Requires-Dist: jinja2>=3.1.6,<4.0.0
Requires-Dist: numpy>=2.0
Requires-Dist: xarray>=2024.7
Requires-Dist: pandas>=2.3.1,<3.0.0
Requires-Dist: matplotlib>=3.10.5,<4.0.0
Requires-Dist: jupyterlab>=4.4.5,<5.0.0
Requires-Dist: dacite>=1.9.2,<2.0.0
Requires-Dist: sympy>=1.14.0,<2.0.0
Requires-Dist: typing-extensions>=4.14.1,<5.0.0
Requires-Dist: black>=25.1.0,<26.0.0
Requires-Dist: xarray ; extra == 'xarray'
Requires-Dist: pandas ; extra == 'pandas'
Requires-Dist: matplotlib ; extra == 'notebooks'
Requires-Dist: xarray ; extra == 'notebooks'
Requires-Dist: pandas ; extra == 'notebooks'
Requires-Dist: jupyterlab ; extra == 'notebooks'
Requires-Dist: sympy ; extra == 'sympy'
Provides-Extra: xarray
Provides-Extra: pandas
Provides-Extra: notebooks
Provides-Extra: sympy
License-File: license
Summary: A Python package for the reproducibility of hardware security experiments.
Author-email: Louis Dubois <ldbo@protonmail.com>
License-Expression: MIT
Requires-Python: >=3.10, <3.14
Project-URL: repository, https://github.com/ldbo/phileas
Project-URL: issues, https://github.com/ldbo/phileas/issues
Project-URL: documentation, https://phileas.readthedocs.io/en/latest/
